Metadata-Version: 1.1
Name: pay-with-amazon
Version: 1.0.1
Summary: Login and Pay with Amazon Python SDK
Home-page: https://github.com/amzn/login-and-pay-with-amazon-sdk-python
Author: EPS-DSE
Author-email: pay-with-amazon-sdk@amazon.com
License: Apache License version 2.0, January 2004
Download-URL: https://github.com/amzn/login-and-pay-with-amazon-sdk-python/tarball/1.0.1
Keywords: Amazon,Payments,Login,Python,API,SDK
Platform: UNKNOWN
Classifier: Development Status :: 5 - Production/Stable
Classifier: Intended Audience :: Developers
Classifier: License :: OSI Approved :: Apache Software License
Classifier: Natural Language :: English
Classifier: Operating System :: OS Independent
Classifier: Programming Language :: Python
Classifier: Programming Language :: Python :: 3.2
Classifier: Programming Language :: Python :: 3.4
Classifier: Topic :: Software Development :: Libraries
Classifier: Topic :: Software Development :: Libraries :: Python Modules
